osm_opening_hours_humanized/__init__.py
osm_opening_hours_humanized/exceptions.py
osm_opening_hours_humanized/field.ebnf
osm_opening_hours_humanized/field_parser.py
osm_opening_hours_humanized/frequent_fields.py
osm_opening_hours_humanized/main.py
osm_opening_hours_humanized/rendering.py
osm_opening_hours_humanized/temporal_objects.py
osm_opening_hours_humanized/version.py
osm_opening_hours_humanized/locales/de/LC_MESSAGES/hoh.mo
osm_opening_hours_humanized/locales/fr_FR/LC_MESSAGES/hoh.mo
osm_opening_hours_humanized/locales/it_IT/LC_MESSAGES/hoh.mo
osm_opening_hours_humanized/locales/nl/LC_MESSAGES/hoh.mo
osm_opening_hours_humanized/locales/pl/LC_MESSAGES/hoh.mo
osm_opening_hours_humanized/locales/pt/LC_MESSAGES/hoh.mo
osm_opening_hours_humanized/locales/ru_RU/LC_MESSAGES/hoh.mo
osm_opening_hours_humanized-1.0.0b7.dist-info/LICENCE
osm_opening_hours_humanized-1.0.0b7.dist-info/METADATA
osm_opening_hours_humanized-1.0.0b7.dist-info/WHEEL
osm_opening_hours_humanized-1.0.0b7.dist-info/top_level.txt
osm_opening_hours_humanized-1.0.0b7.dist-info/RECORD
