Metadata-Version: 2.1
Name: osm-opening-hours-humanized
Version: 1.0.0b7
Summary: A parser for the opening_hours fields from OpenStreetMap.
Home-page: https://github.com/jy95/osm_opening_hours_humanized
Author: rezemika
Author-email: reze.mika@gmail.com
Keywords: openstreetmap opening_hours parser
Classifier: Programming Language :: Python
Classifier: Development Status :: 3 - Alpha
Classifier: Intended Audience :: Developers
Classifier: License :: OSI Approved :: GNU Affero General Public License v3
Classifier: Natural Language :: English
Classifier: Natural Language :: French
Classifier: Operating System :: OS Independent
Classifier: Programming Language :: Python :: 3
Classifier: Topic :: Utilities
Classifier: Topic :: Other/Nonlisted Topic
License-File: LICENCE
Requires-Dist: lark-parser
Requires-Dist: babel
Requires-Dist: astral
